Metadata-Version: 1.0
Name: statdists
Version: 0.1
Summary: Distribution Functions
Home-page: UNKNOWN
Author: Ugur Selim Ozen
Author-email: ugur_ozen58@hotmail.com
License: UNKNOWN
Platform: UNKNOWN
